CCRS/__init__.py
CCRS/kernels.py
CCRS/used.py
CCRS-1.0.0.dist-info/LICENSE.txt
CCRS-1.0.0.dist-info/METADATA
CCRS-1.0.0.dist-info/WHEEL
CCRS-1.0.0.dist-info/top_level.txt
CCRS-1.0.0.dist-info/RECORD
