Metadata-Version: 2.1
Name: CCRS
Version: 1.0.0
Summary: Risk stratification of coronary heart disease and ischemic stroke
Home-page: https://github.com/VVictorChen/CCR
Author: Victor
Author-email: chenweibang@genomics.cn
License: UNKNOWN
Platform: UNKNOWN
Classifier: Programming Language :: Python :: 3
Classifier: License :: OSI Approved :: MIT License
Classifier: Operating System :: OS Independent
Requires-Python: >=3.7
